xcolle_api/__init__.py
xcolle_api/__main__.py
xcolle_api/_common.py
xcolle_api/_css.py
xcolle_api/_tests.py
xcolle_api/_utils.py
xcolle_api/gcolle/__init__.py
xcolle_api/gcolle/models.py
xcolle_api/pcolle/__init__.py
xcolle_api/pcolle/models.py
xcolle_api-0.1.4.dist-info/licenses/LICENSE
xcolle_api-0.1.4.dist-info/WHEEL
xcolle_api-0.1.4.dist-info/entry_points.txt
xcolle_api-0.1.4.dist-info/METADATA
xcolle_api-0.1.4.dist-info/RECORD
