Metadata-Version: 2.4
Name: xcolle-api
Version: 0.1.4
Summary: A Python library providing an asynchronous API interface for pcolle.com / gcolle.net
Author: NTFSvolume
License-Expression: LGPL-3.0-only
License-File: LICENSE
Requires-Dist: aiohttp>=3.12.15
Requires-Dist: aiolimiter>=1.2.1
Requires-Dist: beautifulsoup4>=4.13.4
Requires-Dist: html2text>=2025.4.15
Requires-Python: >=3.11
Project-URL: Homepage, https://github.com/NTFSvolume/xcolle-api
